rsserpent/__init__.py
rsserpent/main.py
rsserpent/models/__init__.py
rsserpent/models/plugin.py
rsserpent/models/rss.py
rsserpent/plugins/__init__.py
rsserpent/plugins/builtin/__init__.py
rsserpent/plugins/builtin/example.py
rsserpent/plugins/builtin/example_cache.py
rsserpent/plugins/builtin/example_httpx.py
rsserpent/plugins/builtin/example_pyppeteer.py
rsserpent/plugins/builtin/example_pyquery.py
rsserpent/plugins/builtin/example_ratelimit.py
rsserpent/plugins/builtin/example_with_args.py
rsserpent/plugins/externals.py
rsserpent/py.typed
rsserpent/templates/exception.html.jinja
rsserpent/templates/index.html.jinja
rsserpent/templates/rss.xml.jinja
rsserpent/utils/__init__.py
rsserpent/utils/cache.py
rsserpent/utils/http.py
rsserpent/utils/provider.py
rsserpent/utils/ratelimit.py
rsserpent-0.1.4.dist-info/LICENSE
rsserpent-0.1.4.dist-info/WHEEL
rsserpent-0.1.4.dist-info/METADATA
rsserpent-0.1.4.dist-info/RECORD
