Metadata-Version: 2.1
Name: rsserpent
Version: 0.1.4
Summary: 🐍 This snake helps you reconnect the Web, with RSS feeds!
Home-page: https://github.com/RSSerpent/RSSerpent
License: MIT
Keywords: rss
Author: Queensferry
Author-email: queensferry.me@gmail.com
Requires-Python: >=3.6.2,<4.0.0
Classifier: Development Status :: 4 - Beta
Classifier: Environment :: Web Environment
Classifier: Framework :: AsyncIO
Classifier: Intended Audience :: Developers
Classifier: Intended Audience :: End Users/Desktop
Classifier: License :: OSI Approved :: MIT License
Classifier: Natural Language :: English
Classifier: Operating System :: OS Independent
Classifier: Programming Language :: Python
Classifier: Programming Language :: Python :: 3
Classifier: Programming Language :: Python :: 3.7
Classifier: Programming Language :: Python :: 3.8
Classifier: Programming Language :: Python :: 3.9
Classifier: Topic :: Internet :: WWW/HTTP :: Dynamic Content :: News/Diary
Classifier: Topic :: Software Development :: Libraries :: Python Modules
Classifier: Topic :: Utilities
Classifier: Typing :: Typed
Requires-Dist: Jinja2 (>=3.0.1,<4.0.0)
Requires-Dist: arrow (>=1.1.1,<2.0.0)
Requires-Dist: fake-useragent (>=0.1.11,<0.2.0)
Requires-Dist: httpx (>=0.19.0,<0.20.0)
Requires-Dist: importlib-metadata (>=4.5.0,<5.0.0)
Requires-Dist: pydantic[email] (>=1.8.2,<2.0.0)
Requires-Dist: pyppeteer (>=0.2.6,<0.3.0)
Requires-Dist: pyquery (>=1.4.3,<2.0.0)
Requires-Dist: starlette (>=0.16.0,<0.17.0)
Project-URL: Repository, https://github.com/RSSerpent/RSSerpent
